{
  "@context": "https://schema.org",
  "@type": [
    "MusicAlbum",
    "Product"
  ],
  "name": "The Silver Gauntlet of Aethel, Book II: The Shadow's Heart (Original Motion Picture Soundtrack)",
  "byArtist": {
    "@type": "MusicGroup",
    "name": "Firelight"
  },
  "albumProductionType": "SoundtrackAlbum",
  "albumReleaseType": "AlbumRelease",
  "genre": "Soundtrack / 80s Rock / Orchestral",
  "datePublished": "2026-04-24",
  "temporalCoverage": "2017-11-21",
  "description": "Part two of the definitive 3-disc 'Leviathan Cut' soundtrack for the Aethel Saga. Book II: The Shadow's Heart plunges into the dark, psychological core of the story, featuring the epic villain anthem 'The Tyrant's Throne' and the emotional climax 'I Can't Live Without You'.",
  "gtin12": "",
  "publisher": {
    "@type": "Organization",
    "name": "DistroKid"
  },
  "conditionsOfAccess": "Pending Distribution",
  "creativeWorkStatus": "Upcoming Release"
}